tenant_schemas/__init__.py
tenant_schemas/apps.py
tenant_schemas/cache.py
tenant_schemas/log.py
tenant_schemas/middleware.py
tenant_schemas/models.py
tenant_schemas/routers.py
tenant_schemas/signals.py
tenant_schemas/storage.py
tenant_schemas/template_loaders.py
tenant_schemas/urlresolvers.py
tenant_schemas/utils.py
tenant_schemas/management/__init__.py
tenant_schemas/management/commands/__init__.py
tenant_schemas/management/commands/collectstatic_schemas.py
tenant_schemas/management/commands/list_tenants.py
tenant_schemas/management/commands/migrate.py
tenant_schemas/management/commands/migrate_schemas.py
tenant_schemas/management/commands/tenant_command.py
tenant_schemas/migration_executors/__init__.py
tenant_schemas/migration_executors/base.py
tenant_schemas/migration_executors/parallel.py
tenant_schemas/migration_executors/standard.py
tenant_schemas/postgresql_backend/__init__.py
tenant_schemas/postgresql_backend/base.py
tenant_schemas/postgresql_backend/introspection.py
tenant_schemas/templatetags/__init__.py
tenant_schemas/templatetags/tenant.py
tenant_schemas/test/__init__.py
tenant_schemas/test/cases.py
tenant_schemas/test/client.py
tenant_schemas/tests/__init__.py
tenant_schemas/tests/models.py
tenant_schemas/tests/test_apps.py
tenant_schemas/tests/test_cache.py
tenant_schemas/tests/test_log.py
tenant_schemas/tests/test_routes.py
tenant_schemas/tests/test_tenants.py
tenant_schemas/tests/test_utils.py
tenant_schemas/tests/testcases.py
django_tenant_schemas_mosi-0.2.dist-info/LICENSE
django_tenant_schemas_mosi-0.2.dist-info/METADATA
django_tenant_schemas_mosi-0.2.dist-info/WHEEL
django_tenant_schemas_mosi-0.2.dist-info/top_level.txt
django_tenant_schemas_mosi-0.2.dist-info/RECORD
