Metadata-Version: 2.1
Name: django-tenant-schemas-mosi
Version: 0.2
Summary: Tenant support for Django using PostgreSQL schemas.
Home-page: https://github.com/jacastrorug/django-tenant-schemas-mosi
Author: Julian Castro Ruge
Author-email: juliancastroruge@gmail.com
License: MIT
Platform: UNKNOWN
Classifier: License :: OSI Approved :: MIT License
Classifier: Framework :: Django
Classifier: Framework :: Django :: 1.11
Classifier: Framework :: Django :: 2.0
Classifier: Framework :: Django :: 2.1
Classifier: Framework :: Django :: 2.2
Classifier: Programming Language :: Python
Classifier: Programming Language :: Python :: 2.7
Classifier: Programming Language :: Python :: 3.6
Classifier: Programming Language :: Python :: 3.7
Classifier: Topic :: Database
Classifier: Topic :: Software Development :: Libraries
Requires-Dist: Django (>=1.11)
Requires-Dist: ordered-set
Requires-Dist: psycopg2-binary
Requires-Dist: six
